file_convert/__init__.py
file_convert-0.0.21.dist-info/METADATA
file_convert-0.0.21.dist-info/WHEEL
file_convert-0.0.21.dist-info/top_level.txt
file_convert-0.0.21.dist-info/RECORD
