Metadata-Version: 2.1
Name: file-convert
Version: 0.0.21
Summary: Package to convert files between various formats: TIFF, JPEG200, PDF
Home-page: UNKNOWN
Author: Rui Meira
Author-email: ruimiguelcm96@gmail.com
License: UNKNOWN
Platform: UNKNOWN
Classifier: Programming Language :: Python :: 3
Classifier: License :: OSI Approved :: MIT License
Classifier: Operating System :: OS Independent
Requires-Python: >=3.6
